eu2020/__init__.py
eu2020/__main__.py
eu2020/app.py
eu2020/common/__init__.py
eu2020/common/budget.py
eu2020/common/event_processor.py
eu2020/common/higher_power_events.py
eu2020/common/name.py
eu2020/common/parties.py
eu2020/common/parties_events.py
eu2020/common/period.py
eu2020/common/utils.py
eu2020/data/__init__.py
eu2020/data/colors.py
eu2020/data/data.py
eu2020/data/ev_admin.py
eu2020/data/ev_admin_eb.py
eu2020/data/ev_admin_ek.py
eu2020/data/ev_admin_er.py
eu2020/data/ev_admin_es.py
eu2020/data/ev_deep_state.py
eu2020/data/ev_deep_state_nbm.py
eu2020/data/ev_deep_state_nez.py
eu2020/data/ev_deep_state_sor.py
eu2020/data/ev_deep_state_who.py
eu2020/data/ev_higher_power.py
eu2020/data/ev_members.py
eu2020/data/ev_members_cz.py
eu2020/data/ev_members_de.py
eu2020/data/ev_members_es.py
eu2020/data/ev_members_fr.py
eu2020/data/ev_members_gr.py
eu2020/data/ev_members_hu.py
eu2020/data/ev_members_it.py
eu2020/data/ev_members_lu.py
eu2020/data/ev_members_pl.py
eu2020/data/ev_others.py
eu2020/data/ev_others_ru.py
eu2020/data/texts.py
eu2020-0.4.0.dist-info/LICENSE
eu2020-0.4.0.dist-info/METADATA
eu2020-0.4.0.dist-info/WHEEL
eu2020-0.4.0.dist-info/entry_points.txt
eu2020-0.4.0.dist-info/top_level.txt
eu2020-0.4.0.dist-info/RECORD
