Metadata-Version: 2.1
Name: eu2020
Version: 0.4.0
Summary: Textová hra Evropská Unie 2020
Home-page: https://github.com/underground-lab/eu2020
Author: Jaroslav Beran, Michal Porteš
Author-email: jaroslav.beran@gmail.com, michalportes1@gmail.com
License: GPL-3.0
Project-URL: Bug Tracker, https://github.com/underground-lab/eu2020/issues
Platform: UNKNOWN
Classifier: Programming Language :: Python :: 3
Classifier: Programming Language :: Python :: 3.6
Classifier: Programming Language :: Python :: 3.7
Classifier: Programming Language :: Python :: 3.8
Classifier: Programming Language :: Python :: 3.9
Classifier: Programming Language :: Python :: 3.10
Requires-Python: >=3.6
License-File: LICENSE
Requires-Dist: rich
